pyapu/__init__.py
pyapu/adapters.py
pyapu/cli.py
pyapu/documents/__init__.py
pyapu/documents/file_utils.py
pyapu/documents/spreadsheet.py
pyapu/documents/text.py
pyapu/plugins/__init__.py
pyapu/plugins/base.py
pyapu/plugins/discovery.py
pyapu/plugins/hooks.py
pyapu/plugins/protocol.py
pyapu/plugins/registry.py
pyapu/plugins/sandbox.py
pyapu/processor.py
pyapu/prompts/__init__.py
pyapu/prompts/builder.py
pyapu/providers/__init__.py
pyapu/providers/base.py
pyapu/providers/gemini.py
pyapu/pydantic_support.py
pyapu/security/__init__.py
pyapu/security/chain.py
pyapu/security/injection.py
pyapu/security/output.py
pyapu/security/sanitizer.py
pyapu/types.py
pyapu-0.3.0.dist-info/METADATA
pyapu-0.3.0.dist-info/WHEEL
pyapu-0.3.0.dist-info/entry_points.txt
pyapu-0.3.0.dist-info/licenses/LICENSE
pyapu-0.3.0.dist-info/RECORD
