Metadata-Version: 2.4
Name: pyapu
Version: 0.3.0
Summary: Structured AI document processing with robust fallback strategies.
License: GPL-3.0-or-later
License-File: LICENSE
Keywords: pdf,ai,llm,extraction,json
Author: aquiles
Author-email: achillezongo07@gmail.com
Requires-Python: >=3.12,<4.0
Classifier: License :: OSI Approved :: GNU General Public License v3 or later (GPLv3+)
Classifier: Programming Language :: Python :: 3
Classifier: Programming Language :: Python :: 3.12
Classifier: Programming Language :: Python :: 3.13
Classifier: Programming Language :: Python :: 3.14
Provides-Extra: all
Provides-Extra: cli
Provides-Extra: ocr
Requires-Dist: click (>=8.1.0,<9.0.0) ; extra == "cli" or extra == "all"
Requires-Dist: google-genai (>=1.53.0,<2.0.0)
Requires-Dist: openai (>=2.8.1,<3.0.0)
Requires-Dist: openpyxl (>=3.1.5,<4.0.0)
Requires-Dist: pandas (>=2.3.3,<3.0.0)
Requires-Dist: pdf2image (>=1.17.0,<2.0.0) ; extra == "ocr" or extra == "all"
Requires-Dist: pdfplumber (>=0.11.8,<0.12.0)
Requires-Dist: pluggy (>=1.5.0,<2.0.0)
Requires-Dist: pydantic (>=2.12.5,<3.0.0)
Requires-Dist: pypdf (>=6.4.0,<7.0.0)
Requires-Dist: pytesseract (>=0.3.10,<0.4.0) ; extra == "ocr" or extra == "all"
Requires-Dist: python-dotenv (>=1.2.1,<2.0.0)
Project-URL: Homepage, https://github.com/Aquilesorei/pyapu
Project-URL: Repository, https://github.com/Aquilesorei/pyapu
